rc_injector/__init__.py
rc_injector/injector.py
rc_injector/py.typed
rc_injector/test_utils.py
rc_injector-0.0.2.dist-info/LICENSE
rc_injector-0.0.2.dist-info/WHEEL
rc_injector-0.0.2.dist-info/METADATA
rc_injector-0.0.2.dist-info/RECORD
