Metadata-Version: 2.1
Name: rc-injector
Version: 0.0.2
Summary: Python dependency injector
Home-page: https://github.com/RevenueCat/rc-injector
License: MIT
Author: Guillermo Perez
Author-email: bisho@revenuecat.com
Requires-Python: >=3.8,<4.0
Classifier: License :: OSI Approved :: MIT License
Classifier: Programming Language :: Python :: 3
Classifier: Programming Language :: Python :: 3.8
Classifier: Programming Language :: Python :: 3.9
Classifier: Programming Language :: Python :: 3.10
Classifier: Programming Language :: Python :: 3.11
Project-URL: Repository, https://github.com/RevenueCat/rc-injector
